{"expireTime":9007200866508515000,"key":"bb3a3e0eb680d8f87112f3669596a100","val":{"name":"IMAGE_PROCESSING","inputPaths":["C:/Users/corya/Documents/Lambda/Portfolio/Portfolio/src/data/images/banner/grey-bg.png"],"outputDir":"C:/Users/corya/Documents/Lambda/Portfolio/Portfolio/public/static/5510d19ef1f992e833f66fa12f9ca09f","args":{"isLazy":false,"operations":[{"outputPath":"d3ebd\\grey-bg.png","args":{"height":950,"width":1250,"cropFocus":17,"toFormat":"png","quality":100,"fit":"cover","background":"rgba(0,0,0,1)"}},{"outputPath":"6257f\\grey-bg.png","args":{"height":1425,"width":1875,"cropFocus":17,"toFormat":"png","quality":100,"fit":"cover","background":"rgba(0,0,0,1)"}}],"pluginOptions":{"base64Width":20,"forceBase64Format":"","useMozJpeg":false,"stripMetadata":true,"lazyImageGeneration":true,"defaultQuality":50,"failOnError":true,"plugins":[]}}}}